soyml/__init__.py
soyml/backends.py
soyml/loader.py
soyml/session.py
soyml/session_ncnn.py
soyml/session_ort.py
soyml/session_torch.py
soyml/session_wonnx.py
soyml-0.3.1.dist-info/METADATA
soyml-0.3.1.dist-info/WHEEL
soyml-0.3.1.dist-info/RECORD
