Metadata-Version: 2.4
Name: soyml
Version: 0.3.1
Summary: 
Author: redthing1
Author-email: redthing1@alt.icu
Requires-Python: >=3.11,<3.15
Classifier: Programming Language :: Python :: 3
Classifier: Programming Language :: Python :: 3.11
Classifier: Programming Language :: Python :: 3.12
Classifier: Programming Language :: Python :: 3.13
Classifier: Programming Language :: Python :: 3.14
Provides-Extra: ncnn
Provides-Extra: ort
Provides-Extra: torch
Provides-Extra: wonnx
Requires-Dist: minlog (>=0.6.0,<0.7.0)
Requires-Dist: ncnn (>=1.0.20230517,<2.0.0) ; extra == "ncnn"
Requires-Dist: numpy (>=2.4.0,<3.0.0)
Requires-Dist: onnx (>=1.20.0,<2.0.0)
Requires-Dist: onnxruntime (>=1.23.2,<2.0.0) ; extra == "ort"
Requires-Dist: torch (>=2.9.1,<3.0.0) ; extra == "torch"
Requires-Dist: torchinfo (==1.8.0) ; extra == "torch"
Requires-Dist: wonnx (>=0.5.0,<0.6.0) ; extra == "wonnx"
